{
    "normativa": "INSTRUCCIONES DE 8 DE MARZO DE 2017, DE LA DIRECCIÓN GENERAL DE PARTICIPACIÓN Y EQUIDAD, POR LAS QUE SE ACTUALIZA EL PROTOCOLO DE DETECCIÓN,IDENTIFICACIÓN DEL ALUMNADO CON NECESIDADES ESPECÍFICAS DE APOYO EDUCATIVO Y ORGANIZACIÓN DE LA RESPUESTA EDUCATIVA.",
    "tipo": "Autonómica",
    "fecha": "2017-03-08",
    "tema": "7. ORGANIZACIÓN DE LA RESPUESTA EDUCATIVA",
    "apartado": "C. DIVERSIFICACIÓN DE LOS PROCEDIMIENTOS E INSTRUMENTOS DE EVALUACIÓN.",
    "contenido": "En ocasiones, la pieza clave en la atención a la diversidad del alumnado, se sitúa en el terreno de\r\nla evaluación de los aprendizajes. Una forma de evaluación uniforme y única, solo beneficiará a un tipo de\r\nalumnado estándar. Es decir, una evaluación única no permite una adecuación a los diferentes estilos,\r\nniveles y ritmos de aprendizaje del alumnado.\r\nPor ello, en este apartado, se ofrecen orientaciones para la realización de una evaluación más\r\ninclusiva, desde una doble vertiente:\r\na) Uso de métodos de evaluación alternativos a las pruebas escritas.\r\nb) Adaptaciones en las pruebas escritas.\r\na) Uso de métodos de evaluación alternativos o complementarios a las pruebas escritas.\r\nLa observación diaria del trabajo del alumnado, es una de las principales vías para la evaluación.\r\nPero esta observación no se podrá realizar si no tenemos claro, previamente, qué queremos observar. Es\r\npreciso un cambio en el enfoque que frecuentemente se da a la elaboración de los indicadores de\r\nevaluación. Es imprescindible transcender de procedimientos de evaluación que se centran únicamente\r\nen la adquisición final de contenidos, sin fijarse en otros aspectos colaterales, e igualmente relevantes,\r\ncomo pueden ser las interacciones entre el alumnado.\r\nAsí mismo, se podrían usar portafolios, registros anecdóticos, diarios de clase, listas de control,\r\nescalas de estimación, etc. Todos ellos están basados en la observación y seguimiento del alumnado, más\r\nque en la realización de una prueba escrita en un momento determinado. Debemos tener en cuenta que,\r\nlo que se pretende es que el alumno o la alumna sepa o haga algo concreto, pero no en un momento\r\nconcreto y único. Un ejemplo claro de una de estas alternativas, puede ser el portafolios. De forma muy\r\nresumida, un portafolios es una carpeta en la que el alumnado va archivando sus producciones de clase,\r\npero con una particularidad: periódicamente se revisa el portafolios y el alumnado tiene la oportunidad de cambiar las producciones que hizo. En caso de encontrar un trabajo mal presentado, hacerlo de nuevo de\r\nforma más adecuada; o, incluso, actividades realizadas de forma incorrecta que, a la luz de los\r\naprendizajes adquiridos, deberían ser corregidas, etc. Estos portafolios pueden ser individuales o\r\ngrupales.\r\nb) Adaptaciones en las pruebas escritas.\r\nSi, además de las formas de evaluación descritas anteriormente, se optase por la realización de\r\npruebas escritas, se enumeran a continuación algunas de las adaptaciones que se podrían realizar a\r\ndichas pruebas:\r\n▪ Adaptaciones de formato: Determinados alumnos o alumnas, pueden requerir una\r\nadaptación de una prueba escrita a un formato que se ajuste más a sus necesidades. Así,\r\nalgunas de estas adaptaciones podrían ser las siguientes:\r\n- Presentación de las preguntas de forma secuenciada y separada (por ejemplo, un\r\ncontrol de 10 preguntas se puede presentar en dos partes de 5 preguntas cada una o\r\nincluso se podría hacer con una pregunta en cada folio hasta llegar a las 10).\r\n- Presentación de los enunciados de forma gráfica o en imágenes además de a través de\r\nun texto escrito.\r\n- Selección de aspectos relevantes y esenciales del contenido que se pretende que el\r\nalumno o la alumna aprendan (se trata de hacer una prueba escrita solo con lo básico\r\nque queremos que aprendan).\r\n- Sustitución de la prueba escrita por una prueba oral o una entrevista, o haciendo uso\r\ndel ordenador.\r\n- Lectura de las preguntas por parte del profesor o profesora.\r\n- Supervisión del examen durante su realización (para no dejar preguntas sin responder,\r\npor ejemplo).\r\n▪ Adaptaciones de tiempo: determinados alumnos y alumnas necesitarán más tiempo para la\r\nrealización de una prueba escrita. Esta adaptación de tiempo no tiene por qué tener\r\nlímites. Una prueba no es una carrera, sino una vía para comprobar si se han adquirido\r\nciertos aprendizajes. De esta forma, el docente podría segmentar una prueba en dos o más\r\ndías o, en su lugar, ocupar también la hora siguiente para finalizar la prueba de evaluación.\r\nEn definitiva y como norma general, estas adaptaciones en las pruebas escritas deben ser\r\naquellas que el alumno o alumna tenga durante el proceso de aprendizaje. Es decir, si hemos estado\r\nadaptando tipos de actividades, presentación de las tareas, tiempos... no tiene sentido que estas mismas\r\nadaptaciones no se hagan en la evaluación. Por otro lado, estas adaptaciones deben ser concebidas\r\ncomo una ayuda para que todo el alumnado pueda demostrar sus competencias y capacidades."
}